nua/autobuild/__init__.py
nua/autobuild/builders/Dockerfile_nua_builder_node14
nua/autobuild/builders/Dockerfile_nua_builder_node16
nua/autobuild/builders/Dockerfile_nua_builder_ruby27
nua/autobuild/builders/Dockerfile_nua_builder_ruby272
nua/autobuild/builders/Dockerfile_nua_builder_ruby31
nua/autobuild/builders/Dockerfile_nua_builder_ruby32
nua/autobuild/builders/__init__.py
nua/autobuild/builders/node14.json
nua/autobuild/builders/node16.json
nua/autobuild/builders/ruby27.json
nua/autobuild/builders/ruby272.json
nua/autobuild/builders/ruby31.json
nua/autobuild/builders/ruby32.json
nua/autobuild/constants.py
nua/autobuild/docker_build_utils.py
nua/autobuild/dockerfiles/Dockerfile_nua_builder_slim
nua/autobuild/dockerfiles/Dockerfile_nua_python_slim
nua/autobuild/dockerfiles/__init__.py
nua/autobuild/main.py
nua/autobuild/nua_image_builder.py
nua/autobuild/nua_wheel_builder.py
nua/autobuild/register_builders.py
nua/autobuild/version.py
nua_autobuild-0.5.14.dist-info/METADATA
nua_autobuild-0.5.14.dist-info/WHEEL
nua_autobuild-0.5.14.dist-info/entry_points.txt
nua_autobuild-0.5.14.dist-info/RECORD
