Metadata-Version: 2.1
Name: nua-autobuild
Version: 0.5.14
Summary: Nua self builder
License: AGPL
Author: Stefane Fermigier
Author-email: sf@abilian.com
Requires-Python: >=3.10,<4.0
Classifier: License :: Other/Proprietary License
Classifier: Programming Language :: Python :: 3
Classifier: Programming Language :: Python :: 3.10
Classifier: Programming Language :: Python :: 3.11
Requires-Dist: docker (>=6.0,<7.0)
Requires-Dist: nua-agent (==0.5.14)
Requires-Dist: nua-lib (==0.5.14)
Requires-Dist: paramiko
Requires-Dist: setuptools
Requires-Dist: tomli (>=2.0.1,<3.0.0)
Requires-Dist: tomli-w (>=1.0.0,<2.0.0)
Requires-Dist: typer[all] (>=0.7.0,<0.8.0)
